onboarding_buddy_client/__init__.py
onboarding_buddy_client/api_client.py
onboarding_buddy_client/api_response.py
onboarding_buddy_client/configuration.py
onboarding_buddy_client/exceptions.py
onboarding_buddy_client/py.typed
onboarding_buddy_client/rest.py
onboarding_buddy_client/api/__init__.py
onboarding_buddy_client/api/batch_api.py
onboarding_buddy_client/api/file_api.py
onboarding_buddy_client/api/sanctions_api.py
onboarding_buddy_client/api/validation_api.py
onboarding_buddy_client/models/__init__.py
onboarding_buddy_client/models/aircraft_sanction_record_m.py
onboarding_buddy_client/models/aircraft_sanctions_check_request_m.py
onboarding_buddy_client/models/aircraft_sanctions_check_response_m.py
onboarding_buddy_client/models/browser_get_batch_response_m.py
onboarding_buddy_client/models/browser_request_m.py
onboarding_buddy_client/models/browser_response_m.py
onboarding_buddy_client/models/browser_result_m.py
onboarding_buddy_client/models/browser_submit_batch_request_m.py
onboarding_buddy_client/models/crypto_wallet_sanctions_check_request_m.py
onboarding_buddy_client/models/crypto_wallet_sanctions_check_response_m.py
onboarding_buddy_client/models/digital_currency_address_m.py
onboarding_buddy_client/models/email_address_get_batch_response_m.py
onboarding_buddy_client/models/email_address_request_m.py
onboarding_buddy_client/models/email_address_response_m.py
onboarding_buddy_client/models/email_address_result_m.py
onboarding_buddy_client/models/email_address_submit_batch_request_m.py
onboarding_buddy_client/models/email_entity_record_m.py
onboarding_buddy_client/models/email_individual_record_m.py
onboarding_buddy_client/models/email_sanction_record_m.py
onboarding_buddy_client/models/entity_sanctions_check_request_m.py
onboarding_buddy_client/models/entity_sanctions_check_response_m.py
onboarding_buddy_client/models/file_container_m.py
onboarding_buddy_client/models/file_download_record_m.py
onboarding_buddy_client/models/file_record_list_response_m.py
onboarding_buddy_client-2.1.0.dist-info/METADATA
onboarding_buddy_client-2.1.0.dist-info/WHEEL
onboarding_buddy_client-2.1.0.dist-info/top_level.txt
onboarding_buddy_client-2.1.0.dist-info/RECORD
